keras_spiking/__init__.py
keras_spiking/callbacks.py
keras_spiking/compat.py
keras_spiking/config.py
keras_spiking/constraints.py
keras_spiking/layers.py
keras_spiking/model_energy.py
keras_spiking/regularizers.py
keras_spiking/version.py
keras_spiking/tests/test_callbacks.py
keras_spiking/tests/test_config.py
keras_spiking/tests/test_constraints.py
keras_spiking/tests/test_layers.py
keras_spiking/tests/test_model_energy.py
keras_spiking/tests/test_regularizers.py
keras_spiking/tests/test_version.py
keras_spiking-0.3.0.dist-info/LICENSE.rst
keras_spiking-0.3.0.dist-info/METADATA
keras_spiking-0.3.0.dist-info/WHEEL
keras_spiking-0.3.0.dist-info/top_level.txt
keras_spiking-0.3.0.dist-info/RECORD
